magia_flow/__init__.py
magia_flow/__main__.py
magia_flow/formal/__init__.py
magia_flow/formal/sby.py
magia_flow/online/__init__.py
magia_flow/online/digitaljs/Dockerfile
magia_flow/online/digitaljs/docker-compose.yml
magia_flow/online/digitaljs/nginx.conf
magia_flow/online/digitaljs.py
magia_flow/oss_cad.py
magia_flow/simulation/__init__.py
magia_flow/simulation/general.py
magia_flow/simulation/surfer.py
magia_flow/simulation/verilator.py
magia_flow-0.2.1.dist-info/LICENSE
magia_flow-0.2.1.dist-info/METADATA
magia_flow-0.2.1.dist-info/WHEEL
magia_flow-0.2.1.dist-info/RECORD
